shedule.py
ani_shedule-1.4.dist-info/LICENSE
ani_shedule-1.4.dist-info/METADATA
ani_shedule-1.4.dist-info/WHEEL
ani_shedule-1.4.dist-info/entry_points.txt
ani_shedule-1.4.dist-info/top_level.txt
ani_shedule-1.4.dist-info/RECORD
