Metadata-Version: 2.1
Name: ani-shedule
Version: 1.4
Summary: A simple to view anime aring date and upcoming anime.
Home-page: https://github.com/Kamanati/Ani-Shedule
Author: Hasan
Author-email: yfor22971@gmail.com
License: MIT
Classifier: Programming Language :: Python :: 3
Classifier: License :: OSI Approved :: MIT License
Classifier: Operating System :: OS Independent
Requires-Python: >=3.6
License-File: LICENSE
Requires-Dist: tqdm ==4.63.0
Requires-Dist: lxml ==5.2.2
Requires-Dist: requests ==2.32.3
Requires-Dist: prompt-toolkit ==3.0.43
